{
  "code": "blenders_and_mixers",
  "labels": { "en_US": "Blenders & mixers" },
  "description": {
    "en_US": "Blend perfection into your kitchen with our 'Blenders and Mixers' family template - a powerful assortment of pre-built attributes to easily manage your culinary essentials, taking your cooking to new heights."
  },
  "attributes": [
    {
      "code": "EAN",
      "labels": { "en_US": "Main Identifier" },
      "type": "pim_catalog_identifier",
      "scopable": false,
      "localizable": false,
      "group": "template",
      "unique": true
    },
    {
      "code": "price",
      "labels": { "en_US": "Price" },
      "type": "pim_catalog_price_collection",
      "scopable": false,
      "localizable": false,
      "group": "template",
      "unique": false
    },
    {
      "code": "product_title",
      "labels": { "en_US": "Product title" },
      "type": "pim_catalog_text",
      "scopable": false,
      "localizable": true,
      "group": "template",
      "unique": false
    },
    {
      "code": "short_description",
      "labels": { "en_US": "Short description" },
      "type": "pim_catalog_textarea",
      "scopable": false,
      "localizable": true,
      "group": "template",
      "unique": false
    },
    {
      "code": "long_description",
      "labels": { "en_US": "Long description" },
      "type": "pim_catalog_textarea",
      "scopable": false,
      "localizable": true,
      "group": "template",
      "unique": false
    },
    {
      "code": "brand",
      "labels": { "en_US": "Brand" },
      "type": "pim_catalog_simpleselect",
      "scopable": false,
      "localizable": false,
      "group": "template",
      "unique": false
    },
    {
      "code": "main_image",
      "labels": { "en_US": "Main image" },
      "type": "pim_catalog_image",
      "scopable": false,
      "localizable": false,
      "group": "template",
      "unique": false
    },
    {
      "code": "detailed_image",
      "labels": { "en_US": "Detailed image" },
      "type": "pim_catalog_image",
      "scopable": false,
      "localizable": false,
      "group": "template",
      "unique": false
    },
    {
      "code": "atmosphere_image",
      "labels": { "en_US": "Atmosphere image" },
      "type": "pim_catalog_image",
      "scopable": false,
      "localizable": false,
      "group": "template",
      "unique": false
    },
    {
      "code": "color",
      "labels": { "en_US": "Color" },
      "type": "pim_catalog_simpleselect",
      "scopable": false,
      "localizable": false,
      "group": "template",
      "unique": false
    },
    {
      "code": "color_name",
      "labels": { "en_US": "Color name" },
      "type": "pim_catalog_text",
      "scopable": false,
      "localizable": true,
      "group": "template",
      "unique": false
    },
    {
      "code": "material",
      "labels": { "en_US": "Material" },
      "type": "pim_catalog_multiselect",
      "scopable": false,
      "localizable": false,
      "group": "template",
      "unique": false
    },
    {
      "code": "recycled_material",
      "labels": { "en_US": "Recycled material" },
      "type": "pim_catalog_boolean",
      "scopable": false,
      "localizable": false,
      "group": "template",
      "unique": false
    },
    {
      "code": "made_in",
      "labels": { "en_US": "Made in" },
      "type": "pim_catalog_simpleselect",
      "scopable": false,
      "localizable": false,
      "group": "template",
      "unique": false
    },
    {
      "code": "wattage",
      "labels": { "en_US": "Wattage" },
      "type": "pim_catalog_metric",
      "scopable": false,
      "localizable": false,
      "group": "template",
      "unique": false,
      "metric_family": "Power"
    },
    {
      "code": "voltage",
      "labels": { "en_US": "Voltage" },
      "type": "pim_catalog_metric",
      "scopable": false,
      "localizable": false,
      "group": "template",
      "unique": false,
      "metric_family": "Power"
    },
    {
      "code": "aesthetics",
      "labels": { "en_US": "Aesthetics" },
      "type": "pim_catalog_simpleselect",
      "scopable": false,
      "localizable": false,
      "group": "template",
      "unique": false
    },
    {
      "code": "finishing",
      "labels": { "en_US": "Finishing" },
      "type": "pim_catalog_simpleselect",
      "scopable": false,
      "localizable": false,
      "group": "template",
      "unique": false
    },
    {
      "code": "length",
      "labels": { "en_US": "Length" },
      "type": "pim_catalog_metric",
      "scopable": false,
      "localizable": false,
      "group": "template",
      "unique": false,
      "metric_family": "Length"
    },
    {
      "code": "height",
      "labels": { "en_US": "Height" },
      "type": "pim_catalog_metric",
      "scopable": false,
      "localizable": false,
      "group": "template",
      "unique": false,
      "metric_family": "Length"
    },
    {
      "code": "weight",
      "labels": { "en_US": "Weight" },
      "type": "pim_catalog_metric",
      "scopable": false,
      "localizable": false,
      "group": "template",
      "unique": false,
      "metric_family": "Weight"
    },
    {
      "code": "capacity",
      "labels": { "en_US": "Capacity" },
      "type": "pim_catalog_metric",
      "scopable": false,
      "localizable": false,
      "group": "template",
      "unique": false,
      "metric_family": "Volume"
    }
  ]
}
